regex4dummies/__init__.py
regex4dummies/compare.py
regex4dummies/dependency.py
regex4dummies/gui_downloader.py
regex4dummies/literal_parsing.py
regex4dummies/nlpnet_parser.py
regex4dummies/nltk_parser.py
regex4dummies/normalizer.py
regex4dummies/pattern_detail.py
regex4dummies/pattern_parser.py
regex4dummies/phrase_extractor.py
regex4dummies/regex4dummies.py
regex4dummies/run_dependency_tests.py
regex4dummies/run_tests.py
regex4dummies/semantic_parsing.py
regex4dummies/string_compare.py
regex4dummies/test_dependencies.py
regex4dummies/tokenizer.py
regex4dummies/toolkit.py
regex4dummies/topic_finder.py
regex4dummies/literal_parsers/__init__.py
regex4dummies/literal_parsers/literal_parsing.py
regex4dummies/semantic_parsers/__init__.py
regex4dummies/semantic_parsers/nlpnet_parser.py
regex4dummies/semantic_parsers/nltk_parser.py
regex4dummies/semantic_parsers/normalizer.py
regex4dummies/semantic_parsers/pattern_parser.py
regex4dummies/tests/__init__.py
regex4dummies/tests/main.py
regex4dummies/tests/literal_tests/__init__.py
regex4dummies/tests/literal_tests/literal_parser_tester.py
regex4dummies/tests/semantic_tests/__init__.py
regex4dummies/tests/semantic_tests/run_semantic_tests.py
regex4dummies/tests/toolkit_tests/__init__.py
regex4dummies/tests/toolkit_tests/toolkit_tests.py
regex4dummies/tests/topic_analysis/__init__.py
regex4dummies/tests/topic_analysis/run_topic_analysis_tests.py
regex4dummies-1.4.6.dist-info/DESCRIPTION.rst
regex4dummies-1.4.6.dist-info/METADATA
regex4dummies-1.4.6.dist-info/metadata.json
regex4dummies-1.4.6.dist-info/pbr.json
regex4dummies-1.4.6.dist-info/RECORD
regex4dummies-1.4.6.dist-info/top_level.txt
regex4dummies-1.4.6.dist-info/WHEEL
