Metadata-Version: 2.0
Name: regex4dummies
Version: 1.4.6
Summary: A NLP library that simplifies pattern finding in strings
Home-page: https://darkmattervale.github.io/regex4dummies
Author: Vale Tolpegin
Author-email: regex4dummies@gmail.com
License: MIT
Keywords: TextBlob,NLTK,Pattern,NLP
Platform: UNKNOWN
Classifier: Development Status :: 3 - Alpha
Classifier: Intended Audience :: Developers
Classifier: Intended Audience :: Education
Classifier: Intended Audience :: Information Technology
Classifier: Intended Audience :: Science/Research
Classifier: Topic :: Scientific/Engineering
Classifier: Topic :: Scientific/Engineering :: Artificial Intelligence
Classifier: Topic :: Scientific/Engineering :: Human Machine Interfaces
Classifier: Topic :: Scientific/Engineering :: Information Analysis
Classifier: Topic :: Text Processing
Classifier: Topic :: Text Processing :: Filters
Classifier: Topic :: Text Processing :: General
Classifier: Topic :: Text Processing :: Indexing
Classifier: Topic :: Text Processing :: Linguistic
Classifier: License :: OSI Approved :: MIT License
Classifier: Programming Language :: Python :: 2.7
Classifier: Operating System :: OS Independent
Requires-Dist: pattern
Requires-Dist: TextBlob
Requires-Dist: nltk
Requires-Dist: nlpnet
Requires-Dist: numpy
Requires-Dist: fuzzywuzzy
Requires-Dist: python-Levenshtein
